setup.cfg
setup.py
./__init__.py
./blog.py
./blog.xml
./tryton.cfg
./tests/__init__.py
./tests/test_blog.py
openlabs_nereid_blog.egg-info/PKG-INFO
openlabs_nereid_blog.egg-info/SOURCES.txt
openlabs_nereid_blog.egg-info/dependency_links.txt
openlabs_nereid_blog.egg-info/entry_points.txt
openlabs_nereid_blog.egg-info/not-zip-safe
openlabs_nereid_blog.egg-info/requires.txt
openlabs_nereid_blog.egg-info/top_level.txt