Metadata-Version: 1.1
Name: openlabs-nereid-blog
Version: 3.0.2.0
Summary: Nereid Blog module
Home-page: http://www.openlabs.co.in/
Author: Openlabs Technologies & Consulting (P) LTD
Author-email: info@openlabs.co.in
License: GPL-3
Platform: UNKNOWN
Classifier: Development Status :: 4 - Beta
Classifier: Environment :: Plugins
Classifier: Intended Audience :: Developers
Classifier: License :: OSI Approved :: GNU General Public License v3 (GPLv3)
Classifier: Natural Language :: English
Classifier: Operating System :: OS Independent
Classifier: Programming Language :: Python
Classifier: Framework :: Tryton
Classifier: Topic :: Office/Business
